transon/__init__.py
transon/docs.py
transon/functions.py
transon/operators.py
transon/rules.py
transon/tests/__init__.py
transon/tests/base.py
transon/tests/base_attr.py
transon/tests/base_join.py
transon/tests/conftest.py
transon/tests/test_attr.py
transon/tests/test_chain.py
transon/tests/test_convert.py
transon/tests/test_expr.py
transon/tests/test_file.py
transon/tests/test_filter.py
transon/tests/test_format.py
transon/tests/test_include.py
transon/tests/test_invalid_value.py
transon/tests/test_join.py
transon/tests/test_map.py
transon/tests/test_no_content.py
transon/transformers.py
transon-0.0.7.dist-info/METADATA
transon-0.0.7.dist-info/WHEEL
transon-0.0.7.dist-info/RECORD
