Metadata-Version: 2.1
Name: transon
Version: 0.0.7
Summary: Homogenous JSON template engine
Home-page: https://github.com/transon-org/transon
License: MIT
Author: Eugene Chernyshov
Author-email: chernyshov.eugene@gmail.com
Requires-Python: >=3.7,<4.0
Classifier: License :: OSI Approved :: MIT License
Classifier: Operating System :: OS Independent
Classifier: Programming Language :: Python :: 3
Classifier: Programming Language :: Python :: 3.7
Classifier: Programming Language :: Python :: 3.8
Classifier: Programming Language :: Python :: 3.9
Classifier: Programming Language :: Python :: 3.10
Classifier: Programming Language :: Python :: 3.11
Classifier: Programming Language :: Python :: 3
Requires-Dist: importlib-metadata (>=6.5.0,<7.0.0) ; python_version == "3.7"
Project-URL: Bug Tracker, https://github.com/transon-org/transon/issues
Project-URL: Documentation, https://transon-org.github.io/
Project-URL: Repository, https://github.com/transon-org/transon
